AUTHORS.txt
CHANGES.txt
MANIFEST.in
README.txt
setup.cfg
setup.py
DB2CSV.egg-info/PKG-INFO
DB2CSV.egg-info/SOURCES.txt
DB2CSV.egg-info/dependency_links.txt
DB2CSV.egg-info/not-zip-safe
DB2CSV.egg-info/requires.txt
DB2CSV.egg-info/top_level.txt
db2csv/__init__.py
db2csv/utf8csv.py
scripts/db2csv_archive