Metadata-Version: 1.1
Name: DB2CSV
Version: 0.1b2
Summary: Tool to dump all database tables into csv files.
Home-page: https://github.com/stefanofontanelli/db2csv
Author: Stefano Fontanelli
Author-email: s.fontanelli@asidev.com
License: UNKNOWN
Keywords: database sqlalchemy archive tools
Platform: UNKNOWN
Classifier: Programming Language :: Python
Classifier: Topic :: Database
